comdev/__init__.py
comdev/etherpad_api.py
comdev/facebook_api.py
comdev/firebase_api.py
comdev/gmail_api.py
comdev/google_api.py
comdev/ical_api.py
comdev/ldap_api.py
comdev/lib.py
comdev/meetup_api.py
comdev/rss_lib.py
comdev/twitter_api.py
comdev/visa.py
comdev-0.2.1.data/scripts/comdev
comdev-0.2.1.dist-info/METADATA
comdev-0.2.1.dist-info/RECORD
comdev-0.2.1.dist-info/WHEEL
comdev-0.2.1.dist-info/dependency_links.txt
comdev-0.2.1.dist-info/top_level.txt
