Metadata-Version: 2.1
Name: comdev
Version: 0.2.1
Summary: Community Development support library
Home-page: https://github.com/kejbaly2/comdev
Author: Chris Ward
Author-email: cward@redhat.com
License: GPLv3
Platform: UNKNOWN
Requires-Dist: babel
Requires-Dist: click
Requires-Dist: confuse
Requires-Dist: python-dateutil
Requires-Dist: google-api-python-client
Requires-Dist: jinja2
Requires-Dist: premailer
Requires-Dist: progressbar2
Requires-Dist: requests
